operacionjgg/MathOperations.py
operacionjgg/__init__.py
operacionjgg-1.0.dist-info/METADATA
operacionjgg-1.0.dist-info/WHEEL
operacionjgg-1.0.dist-info/top_level.txt
operacionjgg-1.0.dist-info/RECORD
