Metadata-Version: 2.1
Name: operacionjgg
Version: 1.0
Summary: Operaciones Matematicas
Home-page: https://dina.concytec.gob.pe/appDirectorioCTI/VerDatosInvestigador.do?id_investigador=12581
Author: Jorge Guerra Guerra
Author-email: jguerra91@gmail.com
License: UNKNOWN
Platform: UNKNOWN
